{

  "test": [

    {

      "pos": "1",

      "img": "https://www.cricbuzz.com/i/stats/fw/50x50/img/faceImages/8095.jpg",

      "cn": "AUS",

      "name": "Pat Cummins",

      "rate": "878"



    },
    {



      "pos": "2",

      "img": "https://www.cricbuzz.com/i/stats/fw/50x50/img/faceImages/65.jpg",

      "cn": "ENG",

      "name": "James Andrson",

      "rate": "862"



    },
    {

      "pos": "3",

      "img": "https://www.cricbuzz.com/i/stats/fw/50x50/img/faceImages/9585.jpg",

      "cn": "SA",

      "name": "Kagiso Rabada",

      "rate": "851"
    },



    {



      "pos": "4",

      "img": "https://www.cricbuzz.com/i/stats/fw/50x50/img/faceImages/731.jpg",

      "cn": "SA",

      "name": "Vernon Philander",

      "rate": "813"



    },



    {



      "pos": "5",

      "img": "https://www.cricbuzz.com/i/stats/fw/50x50/img/faceImages/2257.jpg",

      "cn": "NZ",

      "name": "Neil Wagner",

      "rate": "801"

    },

    {



      "pos": "6",

      "img": "https://www.cricbuzz.com/i/stats/fw/50x50/img/faceImages/587.jpg",

      "cn": "IND",

      "name": "Ravindra Jadeja",

      "rate": "794"



    },



    {



      "pos": "7",

      "img": "https://www.cricbuzz.com/i/stats/fw/50x50/img/faceImages/8117.jpg",

      "cn": "NZ",

      "name": "Trent Boult",

      "rate": "787"



    },



    {

      "pos": "8",

      "img": "https://www.cricbuzz.com/i/stats/fw/50x50/img/faceImages/11298.jpg",

      "cn": "PAK",

      "name": "Mohammad Abbas",

      "rate": "770"



    },



    {

     "pos": "9",

      "img": "https://www.cricbuzz.com/i/stats/fw/50x50/img/faceImages/8313.jpg",

      "cn": "WI",

      "name": "Json Holder",

      "rate": "770"



    },



    {

      "pos": "10",

      "img": "https://www.cricbuzz.com/i/stats/fw/50x50/img/faceImages/1593.jpg",

      "cn": "IND",

      "name": "Ravichandran Ashwin",

      "rate": "763"

    },

     {

      "pos": "11",

      "img": "https://www.cricbuzz.com/i/stats/fw/50x50/img/faceImages/1359.jpg",

      "cn": "WI",

      "name": "Kemar Roach",

      "rate": "744"

    },

     {

      "pos": "12",

      "img": "https://www.cricbuzz.com/i/stats/fw/50x50/img/faceImages/1057.jpg",

      "cn": "NZ",

      "name": "Tim Southee",

      "rate": "736"

    },

     {

      "pos": "13",

      "img": "https://www.cricbuzz.com/i/stats/fw/50x50/img/faceImages/6258.jpg",

      "cn": "AUS",

      "name": "Josh Hazlewood",

      "rate": "728"

    },

     {

      "pos": "14",

      "img": "https://www.cricbuzz.com/i/stats/fw/50x50/img/faceImages/8092.jpg",

      "cn": "WI",

      "name": "Shannon Gabriel",

      "rate": "725"

    },

     {

      "pos": "15",

      "img": "https://www.cricbuzz.com/i/stats/fw/50x50/img/faceImages/7710.jpg",

      "cn": "AUS",

      "name": "Mitchell Starc",

      "rate": "719"

    },

     {

      "pos": "16",

      "img": "https://www.cricbuzz.com/i/stats/fw/50x50/img/faceImages/9311.jpg",

      "cn": "IND",

      "name": "Jasprit Bumrah",

      "rate": "711"

    },

     {

      "pos": "17",

      "img": "https://www.cricbuzz.com/i/stats/fw/50x50/img/faceImages/8064.jpg",

      "cn": "PAK",

      "name": "Yasir Shah",

      "rate": "710"

    },

     {

      "pos": "18",

      "img": "https://www.cricbuzz.com/i/stats/fw/50x50/img/faceImages/7850.jpg",

      "cn": "AUS",

      "name": "Nathon Lyon",

      "rate": "690"

    },

     {

      "pos": "19",

      "img": "https://www.cricbuzz.com/i/stats/fw/50x50/img/faceImages/554.jpg",

      "cn": "ENG",

      "name": "Stuart Broad",

      "rate": "680"

    },

     {

      "pos": "20",

      "img": "https://www.cricbuzz.com/i/stats/fw/50x50/img/faceImages/544.jpg",

      "cn": "BAN",

      "name": "Shakib Al Hasan",

      "rate": "662"

    }

  ]

}
